dcinside/__init__.py
dcinside/crawler.py
dcinside/exception.py
dc_crawler-1.0.0.dist-info/LICENSE
dc_crawler-1.0.0.dist-info/METADATA
dc_crawler-1.0.0.dist-info/WHEEL
dc_crawler-1.0.0.dist-info/top_level.txt
dc_crawler-1.0.0.dist-info/RECORD
